{
  "二階堂 三鄉": {
    "value": "二階堂 三鄉",
    "names": { "zh-TW": "二階堂 三鄉", "jp": "二階堂 三郷" },
    "english name": "Misato_Nikaido",
    "style": {
      "最年少名人": {
        "value": "最年少名人",
        "names": { "zh-TW": "最年少名人", "jp": "最年少名人" },
        "id": "001"
      },
      "今昔之感，思緒萬千": {
        "value": "今昔之感，思緒萬千",
        "names": { "zh-TW": "今昔之感，思緒萬千", "jp": "今昔の感、想いは往きて" },
        "id": "002"
      },
      "甜蜜的悠閒時光": {
        "value": "甜蜜的悠閒時光",
        "names": { "zh-TW": "甜蜜的悠閒時光", "jp": "甘い悠々時光" },
        "id": "004"
      },
      "至高無上的終局": {
        "value": "至高無上的終局",
        "names": { "zh-TW": "至高無上的終局", "jp": "無上の終局" },
        "id": "003"
      },
      "Holiday Ring a Bell": {
        "value": "Holiday Ring a Bell",
        "names": { "zh-TW": "Holiday Ring a Bell", "jp": "Holiday Ring a Bell" },
        "id": "005"
      },
      "Lead by Example": {
        "value": "Lead by Example",
        "names": { "zh-TW": "Lead by Example", "jp": "Lead by Example" },
        "id": "006"
      }
    },
    "skill": {
      "common": {
        "扳殺": {
          "value": "扳殺",
          "names": { "zh-TW": "扳殺", "jp": "ハネ殺し" },
          "sp": 5
        },
        "冷卻": {
          "value": "冷卻",
          "names": { "zh-TW": "冷卻", "jp": "クールダウン" },
          "sp": 5
        },
        "究極的一手": {
          "value":"究極的一手",
          "names": { "zh-TW": "究極的一手", "jp": "極点の一手" },
          "sp": 8
        },
        "石塔的手筋": {
          "value": "石塔的手筋",
          "names": { "zh-TW": "石塔的手筋", "jp": "石塔の手筋" },
          "sp": 11
        },
        "石塔的手筋+": {
          "value": "石塔的手筋+",
          "names": { "zh-TW": "石塔的手筋+", "jp": "石塔の手筋+" },
          "sp": 11
        },
        "北風的昴星": {
          "value":"北風的昴星",
          "names": { "zh-TW": "北風的昴星", "jp": "北風のスバル" },
          "sp": 4
        },
        "補充甜點！": {
          "value": "補充甜點！",
          "names": { "zh-TW": "補充甜點！", "jp": "スイーツチャージ！" },
          "sp": 5
        },
        "優勢": {
          "value": "優勢",
          "names": { "zh-TW": "優勢", "jp": "追風" },
          "sp": 12
        }
      },
      "Holiday Ring a Bell": {
        "冰凍圓舞曲": {
          "value": "冰凍圓舞曲",
          "names": { "zh-TW": "冰凍圓舞曲", "jp": "フローズン・ワルツ" },
          "sp": 14
        }
      },
      "Lead by Example": {
        "國士無雙": {
          "value": "國士無雙",
          "names": { "zh-TW": "國士無雙", "jp": "国士無双" },
          "sp": 13
        }
      }
    },
    "passive skill": {}
  },
  "石井 色葉": {
    "value": "石井 色葉",
    "names": { "zh-TW": "石井 色葉", "jp": "石井 色葉" },
    "english name": "Iroha_Ishii",
    "style": {
      "輕鬆多彩": {
        "value": "輕鬆多彩",
        "names": { "zh-TW": "輕鬆多彩", "jp": "お気楽カラフル" },
        "id": "001"
      },
      "色彩繽紛的靈感": {
        "value": "色彩繽紛的靈感",
        "names": { "zh-TW": "色彩繽紛的靈感", "jp": "多彩なるインスピレーション" },
        "id": "002"
      },
      "純粹情感": {
        "value": "純粹情感",
        "names": { "zh-TW": "純粹情感", "jp": "ピュア・エモーション" },
        "id": "003"
      },
      "破壞無彩色之牆": {
        "value": "破壞無彩色之牆",
        "names": { "zh-TW": "破壞無彩色之牆", "jp": "撃砕の無彩色" },
        "id": "004"
      },
      "滿溢的情感": {
        "value": "滿溢的情感",
        "names": { "zh-TW": "滿溢的情感", "jp": "センシティビティ・オーバーフロー" },
        "id": "005"
      }
    },
    "skill": {
      "common": {
        "增強": {
          "value": "增強",
          "names": { "zh-TW": "增強", "jp": "エンハンス" },
          "sp": 6
        },
        "極彩射擊": {
          "value": "極彩射擊",
          "names": { "zh-TW": "極彩射擊", "jp": "ヴィヴィットシュート" },
          "sp": 5
        },
        "戰鬥熱情": {
          "value": "戰鬥熱情",
          "names": { "zh-TW": "戰鬥熱情", "jp": "ファイトパッション" },
          "sp": 7
        },
        "飽和增強": {
          "value": "飽和增強",
          "names": { "zh-TW": "飽和增強", "jp": "フィルエンハンス" },
          "sp": 9
        },
        "無色子彈": {
          "value": "無色子彈",
          "names": { "zh-TW": "無色子彈", "jp": "アクロマティックバレット" },
          "sp": 12
        },
        "無色子彈+": {
          "value": "無色子彈+",
          "names": { "zh-TW": "無色子彈+", "jp": "アクロマティックバレット+" },
          "sp": 12
        },
        "五彩繽紛": {
          "value": "五彩繽紛",
          "names": { "zh-TW": "五彩繽紛", "jp": "極彩色" },
          "sp": 10
        }
      },
      "滿溢的情感": {
        "奇觀藝術": {
          "value": "奇觀藝術",
          "names": { "zh-TW": "奇觀藝術", "jp": "スペクタクルアート" },
          "sp": 14
        }
      }
    },
    "passive skill": {}
  },
  "命 吹雪": {
    "value": "命 吹雪",
    "names": { "zh-TW": "命 吹雪", "jp": "命 吹雪" },
    "english name": "Fubuki_Mikoto",
    "style": {
      "Metal Crazy": {
        "value": "Metal Crazy",
        "names": { "zh-TW": "Metal Crazy", "jp": "Metal Crazy" },
        "id": "001"
      },
      "Silent Reverberations": {
        "value": "Silent Reverberations",
        "names": { "zh-TW": "Silent Reverberations", "jp": "Silent Reverberations" },
        "id": "002"
      },
      "末日要幹嘛？": {
        "value": "末日要幹嘛？",
        "names": { "zh-TW": "末日要幹嘛？", "jp": "終末なにする？" },
        "id": "003"
      },
      "Frozen Moon, Melting Heart": {
        "value": "Frozen Moon, Melting Heart",
        "names": { "zh-TW": "Frozen Moon, Melting Heart", "jp": "Frozen Moon, Melting Heart" },
        "id": "004"
      }
    },
    "skill": {
      "common": {
        "狂怒嘶吼": {
          "value": "狂怒嘶吼",
          "names": { "zh-TW": "狂怒嘶吼", "jp": "レイジングシャウト" },
          "sp": 5
        },
        "R.I.P.": {
          "value": "R.I.P.",
          "names": { "zh-TW": "R.I.P.", "jp": "R.I.P." },
          "sp": 7
        },
        "可別先掛點了啊": {
          "value": "可別先掛點了啊",
          "names": { "zh-TW": "可別先掛點了啊", "jp": "先に逝くなよ" },
          "sp": 6
        },
        "以破滅道晚安": {
          "value": "以破滅道晚安",
          "names": { "zh-TW": "以破滅道晚安", "jp": "破滅でおやすみ" },
          "sp": 13
        },
        "以破滅道晚安+": {
          "value": "以破滅道晚安+",
          "names": { "zh-TW": "以破滅道晚安+", "jp": "破滅でおやすみ+" },
          "sp": 12
        },
        "補償": {
          "value": "補償",
          "names": { "zh-TW": "補償", "jp": "コンペンセーション" },
          "sp": 5
        }
      },
      "Frozen Moon, Melting Heart": {
        "給你的禮物": {
          "value": "給你的禮物",
          "names": { "zh-TW": "給你的禮物", "jp": "プレゼント・フォー・ユー" },
          "sp": 16
        }
      }
    },
    "passive skill": {}
  },
  "室伏 理沙": {
    "value": "室伏 理沙",
    "names": { "zh-TW": "室伏 理沙", "jp": "室伏 理沙" },
    "english name": "Risa_Murofushi",
    "style": {
      "母愛的接球手": {
        "value": "母愛的接球手",
        "names": { "zh-TW": "母愛的接球手", "jp": "親愛のレシーバー" },
        "id": "001"
      },
      "痛痛飛走～♪": {
        "value": "痛痛飛走～♪",
        "names": { "zh-TW": "痛痛飛走～♪", "jp": "痛いの痛いの飛んでけ〜♪" },
        "id": "002"
      },
      "蔚藍之花": {
        "value": "蔚藍之花",
        "names": { "zh-TW": "蔚藍之花", "jp": "あまいろの花" },
        "id": "003"
      },
      "溫馨時光": {
        "value": "溫馨時光",
        "names": { "zh-TW": "溫馨時光", "jp": "ハートフルデイズ" },
        "id": "006"
      },
      "趕快回家吧": {
        "value": "趕快回家吧",
        "names": { "zh-TW": "趕快回家吧", "jp": "早くおうちに帰りましょ" },
        "id": "004"
      },
      "潛入，面帶笑容參加技術交流會": {
        "value": "潛入，面帶笑容參加技術交流會",
        "names": { "zh-TW": "潛入，面帶笑容參加技術交流會", "jp": "潜入、笑顔で技術交流会" },
        "id": "005"
      },
      "今晚，在櫻花照映之下": {
        "value": "今晚，在櫻花照映之下",
        "names": { "zh-TW": "今晚，在櫻花照映之下", "jp": "今宵、花明かりの下で" },
        "id": "007"
      }
    },
    "skill": {
      "common": {
        "回復": {
          "value": "回復",
          "names": { "zh-TW": "回復", "jp": "リカバー" },
          "sp": 5
        },
        "重生彈": {
          "value": "重生彈",
          "names": { "zh-TW": "重生彈", "jp": "リバースショット" },
          "sp": 5
        },
        "淒美覺醒": {
          "value": "淒美覺醒",
          "names": { "zh-TW": "淒美覺醒", "jp": "儚き目覚め" },
          "sp": 7
        },
        "飽和回復": {
          "value": "飽和回復",
          "names": { "zh-TW": "飽和回復", "jp": "フィルリカバー" },
          "sp": 8
        },
        "暖心轟炸機": {
          "value": "暖心轟炸機",
          "names": { "zh-TW": "暖心轟炸機", "jp": "ハートフル・ボマー" },
          "sp": 14
        },
        "療癒微笑": {
          "value": "療癒微笑",
          "names": { "zh-TW": "療癒微笑", "jp": "癒やされスマイル" },
          "sp": 5
        },
        "活力綻放": {
          "value": "活力綻放",
          "names": { "zh-TW": "活力綻放", "jp": "バウンシー・ブルーミー" },
          "sp": 8
        },
        "天之微笑": {
          "value": "天之微笑",
          "names": { "zh-TW": "天之微笑", "jp": "天の微笑み" },
          "sp": 4
        }
      },
      "潛入，面帶笑容參加技術交流會": {
        "智慧的恩賜": {
          "value": "智慧的恩賜",
          "names": { "zh-TW": "智慧的恩賜", "jp": "叡智の賜物" },
          "sp": 14
        }
      },
      "今晚，在櫻花照映之下": {
        "蝶之邀約，照耀初旭": {
          "value": "蝶之邀約，照耀初旭",
          "names": { "zh-TW": "蝶之邀約，照耀初旭", "jp": "胡蝶のいざない、照る初旭" },
          "sp": 9
        }
      }
    },
    "passive skill": {
      "真心款待": {
        "value": "真心款待",
        "names": { "zh-TW": "真心款待", "jp": "ふるまうまごころ" }
      }
    }
  },
  "伊達 朱里": {
    "value": "伊達 朱里",
    "names": { "zh-TW": "伊達 朱里", "jp": "伊達 朱里" },
    "english name": "Akari_Date",
    "style": {
      "悲觀王牌": {
        "value": "悲觀王牌",
        "names": { "zh-TW": "悲觀王牌", "jp": "ネガティブエース" },
        "id": "001"
      },
      "完美接招": {
        "value": "完美接招",
        "names": { "zh-TW": "完美接招", "jp": "マーベルアプローチ" },
        "id": "002"
      },
      "網球場惡魔": {
        "value": "網球場惡魔",
        "names": { "zh-TW": "網球場惡魔", "jp": "テニスコートの悪魔" },
        "id": "003"
      },
      "Holiday Star Night": {
        "value": "Holiday Star Night",
        "names": { "zh-TW": "Holiday Star Night", "jp": "Holiday Star Night" },
        "id": "004"
      },
      "幸運冬麗": {
        "value": "幸運冬麗",
        "names": { "zh-TW": "幸運冬麗", "jp": "幸運ふゆうらら" },
        "id": "005"
      }
    },
    "skill": {
      "common": {
        "發球得分": {
          "value": "發球得分",
          "names": { "zh-TW": "發球得分", "jp": "サービス・エース" },
          "sp": 5
        },
        "切削球": {
          "value": "切削球",
          "names": { "zh-TW": "切削球", "jp": "スライスショット" },
          "sp": 8
        },
        "被害妄想": {
          "value": "被害妄想",
          "names": { "zh-TW": "被害妄想", "jp": "被害妄想" },
          "sp": 4
        },
        "漆黑迷幻發球": {
          "value": "漆黑迷幻發球",
          "names": { "zh-TW": "漆黑迷幻發球", "jp": "漆黒トランスサーブ" },
          "sp": 14
        },
        "雪崩": {
          "value": "雪崩",
          "names": { "zh-TW": "雪崩", "jp": "アバランチ" },
          "sp": 8
        },
        "幸運機會": {
          "value": "幸運機會",
          "names": { "zh-TW": "幸運機會", "jp": "ラッキーチャンス" },
          "sp": 7
        },
        "忍術·鵪鶉隱身術": {
          "value": "忍術·鵪鶉隱身術",
          "names": { "zh-TW": "忍術·鵪鶉隱身術", "jp": "忍法・うずら隠れの術" },
          "sp": 6
        }
      },
      "Holiday Star Night": {
        "哀傷的雪花蓮": {
          "value": "哀傷的雪花蓮",
          "names": { "zh-TW": "哀傷的雪花蓮", "jp": "哀のスノードロップ" },
          "sp": 14
        }
      },
      "幸運冬麗": {
        "過熱祈禱": {
          "value": "過熱祈禱",
          "names": { "zh-TW": "過熱祈禱", "jp": "御祈祷オーバーヒート" },
          "sp": 16
        }
      }
    },
    "passive skill": {}
  },
  "瑞原 藍娜": {
    "value": "瑞原 藍娜",
    "names": { "zh-TW": "瑞原 藍娜", "jp": "瑞原 あいな" },
    "english name": "Aina_Mizuhara",
    "style": {
      "深海的學習者": {
        "value": "深海的學習者",
        "names": { "zh-TW": "深海的學習者", "jp": "深き海の学び手" },
        "id": "001"
      },
      "來自深淵的邀請": {
        "value": "來自深淵的邀請",
        "names": { "zh-TW": "來自深淵的邀請", "jp": "アビスからの誘い" },
        "id": "002"
      },
      "品嘗深奧滋味": {
        "value": "品嘗深奧滋味",
        "names": { "zh-TW": "品嘗深奧滋味", "jp": "奥深い味わいを" },
        "id": "003"
      },
      "禁錮虎鯨": {
        "value": "禁錮虎鯨",
        "names": { "zh-TW": "禁錮虎鯨", "jp": "ロックアップオルカ" },
        "id": "004"
      },
      "衝鋒！擊刺！鮪魚！": {
        "value": "衝鋒！擊刺！鮪魚！",
        "names": { "zh-TW": "衝鋒！擊刺！鮪魚！", "jp": "ラッシュ！スタブ！ツナ！" },
        "id": "005"
      },
      "獻給大海的愛情": {
        "value": "獻給大海的愛情",
        "names": { "zh-TW": "獻給大海的愛情", "jp": "溟海に捧ぐアフェクション" },
        "id": "006"
      }
    },
    "skill": {
      "common": {
        "皺鰓鯊硬刃": {
          "value": "皺鰓鯊硬刃",
          "names": { "zh-TW": "皺鰓鯊硬刃", "jp": "ラブカ・ブレード" },
          "sp": 6
        },
        "深層吐息": {
          "value": "深層吐息",
          "names": { "zh-TW": "深層吐息", "jp": "ディープブロー" },
          "sp": 5
        },
        "出刃菜刀登場": {
          "value": "出刃菜刀登場",
          "names": { "zh-TW": "出刃菜刀登場", "jp": "デバノデバン" },
          "sp": 8
        },
        "浩瀚大海": {
          "value": "浩瀚大海",
          "names": { "zh-TW": "浩瀚大海", "jp": "大海原" },
          "sp": 8
        },
        "大海不良分子": {
          "value": "大海不良分子",
          "names": { "zh-TW": "大海不良分子", "jp": "海のギャング" },
          "sp": 15
        },
        "神經痛": {
          "value": "神經痛",
          "names": { "zh-TW": "神經痛", "jp": "ヌラルジャ" },
          "sp": 12
        }
      },
      "衝鋒！擊刺！鮪魚！": {
        "豪邁！海盜加農炮": {
          "value": "豪邁！海盜加農炮",
          "names": { "zh-TW": "豪邁！海盜加農炮", "jp": "豪快！パイレーツキャノン" },
          "sp": 7
        }
      },
      "獻給大海的愛情": {
        "水母之舞": {
          "value": "水母之舞",
          "names": { "zh-TW": "水母之舞", "jp": "ジェリーフィッシュ・ダンス" },
          "sp": 15
        }
      }
    },
    "passive skill": {
      "水光的波動": {
        "value": "水光的波動",
        "names": { "zh-TW": "水光的波動", "jp": "水光のゆらめき" }
      }
    }
  }
}
